Workbook

Sheet 看板
A1: 2026 上半年销售业绩看板
A2: 数据区间 2026-01-01 至 2026-06-30 ｜ 金额单位：元 ｜ 数据源：销售明细
A4: 总销售额 | C4: 总毛利 | E4: 综合毛利率 | G4: 订单总数
A5: ==B15 | C5: ==C15 | E5: ==IF(B15=0,0,C15/B15) | G5: ==D24
A7: 月度销售趋势
A8: 月份 | B8: 销售额 | C8: 毛利 | D8: 毛利率 | E8: 环比增长
A9: 1 | B9: =SUMIFS(销售明细!$J$2:$J$121,销售明细!$M$2:$M$121,$A9) | C9: =SUMIFS(销售明细!$K$2:$K$121,销售明细!$M$2:$M$121,$A9) | D9: =IF(B9=0,0,C9/B9)
A10: 2 | B10: =SUMIFS(销售明细!$J$2:$J$121,销售明细!$M$2:$M$121,$A10) | C10: =SUMIFS(销售明细!$K$2:$K$121,销售明细!$M$2:$M$121,$A10) | D10: =IF(B10=0,0,C10/B10) | E10: =IF(B9=0,0,B10/B9-1)
A11: 3 | B11: =SUMIFS(销售明细!$J$2:$J$121,销售明细!$M$2:$M$121,$A11) | C11: =SUMIFS(销售明细!$K$2:$K$121,销售明细!$M$2:$M$121,$A11) | D11: =IF(B11=0,0,C11/B11) | E11: =IF(B10=0,0,B11/B10-1)
A12: 4 | B12: =SUMIFS(销售明细!$J$2:$J$121,销售明细!$M$2:$M$121,$A12) | C12: =SUMIFS(销售明细!$K$2:$K$121,销售明细!$M$2:$M$121,$A12) | D12: =IF(B12=0,0,C12/B12) | E12: =IF(B11=0,0,B12/B11-1)
A13: 5 | B13: =SUMIFS(销售明细!$J$2:$J$121,销售明细!$M$2:$M$121,$A13) | C13: =SUMIFS(销售明细!$K$2:$K$121,销售明细!$M$2:$M$121,$A13) | D13: =IF(B13=0,0,C13/B13) | E13: =IF(B12=0,0,B13/B12-1)
A14: 6 | B14: =SUMIFS(销售明细!$J$2:$J$121,销售明细!$M$2:$M$121,$A14) | C14: =SUMIFS(销售明细!$K$2:$K$121,销售明细!$M$2:$M$121,$A14) | D14: =IF(B14=0,0,C14/B14) | E14: =IF(B13=0,0,B14/B13-1)
A15: 合计 | B15: =SUM(B9:B14) | C15: =SUM(C9:C14) | D15: =IF(B15=0,0,C15/B15)
A17: 区域销售业绩
A18: 区域 | B18: 销售额 | C18: 占比 | D18: 订单数 | E18: 半年目标 | F18: 达成率
A19: 华东 | B19: =SUMIFS(销售明细!$J$2:$J$121,销售明细!$C$2:$C$121,$A19) | C19: =IF($B$24=0,0,B19/$B$24) | D19: =COUNTIF(销售明细!$C$2:$C$121,$A19) | E19: =参数设置!B5 | F19: =IF(E19=0,0,B19/E19)
A20: 华南 | B20: =SUMIFS(销售明细!$J$2:$J$121,销售明细!$C$2:$C$121,$A20) | C20: =IF($B$24=0,0,B20/$B$24) | D20: =COUNTIF(销售明细!$C$2:$C$121,$A20) | E20: =参数设置!B6 | F20: =IF(E20=0,0,B20/E20)
A21: 华北 | B21: =SUMIFS(销售明细!$J$2:$J$121,销售明细!$C$2:$C$121,$A21) | C21: =IF($B$24=0,0,B21/$B$24) | D21: =COUNTIF(销售明细!$C$2:$C$121,$A21) | E21: =参数设置!B7 | F21: =IF(E21=0,0,B21/E21)
A22: 西南 | B22: =SUMIFS(销售明细!$J$2:$J$121,销售明细!$C$2:$C$121,$A22) | C22: =IF($B$24=0,0,B22/$B$24) | D22: =COUNTIF(销售明细!$C$2:$C$121,$A22) | E22: =参数设置!B8 | F22: =IF(E22=0,0,B22/E22)
A23: 华中 | B23: =SUMIFS(销售明细!$J$2:$J$121,销售明细!$C$2:$C$121,$A23) | C23: =IF($B$24=0,0,B23/$B$24) | D23: =COUNTIF(销售明细!$C$2:$C$121,$A23) | E23: =参数设置!B9 | F23: =IF(E23=0,0,B23/E23)
A24: 合计 | B24: =SUM(B19:B23) | C24: =IF($B$24=0,0,B24/$B$24) | D24: =SUM(D19:D23) | E24: =SUM(E19:E23) | F24: =IF(E24=0,0,B24/E24)
A26: 产品类别销售
A27: 产品类别 | B27: 销售额 | C27: 毛利 | D27: 毛利率 | E27: 占比
A28: 笔记本电脑 | B28: =SUMIFS(销售明细!$J$2:$J$121,销售明细!$E$2:$E$121,$A28) | C28: =SUMIFS(销售明细!$K$2:$K$121,销售明细!$E$2:$E$121,$A28) | D28: =IF(B28=0,0,C28/B28) | E28: =IF($B$33=0,0,B28/$B$33)
A29: 显示器 | B29: =SUMIFS(销售明细!$J$2:$J$121,销售明细!$E$2:$E$121,$A29) | C29: =SUMIFS(销售明细!$K$2:$K$121,销售明细!$E$2:$E$121,$A29) | D29: =IF(B29=0,0,C29/B29) | E29: =IF($B$33=0,0,B29/$B$33)
A30: 键鼠外设 | B30: =SUMIFS(销售明细!$J$2:$J$121,销售明细!$E$2:$E$121,$A30) | C30: =SUMIFS(销售明细!$K$2:$K$121,销售明细!$E$2:$E$121,$A30) | D30: =IF(B30=0,0,C30/B30) | E30: =IF($B$33=0,0,B30/$B$33)
A31: 存储设备 | B31: =SUMIFS(销售明细!$J$2:$J$121,销售明细!$E$2:$E$121,$A31) | C31: =SUMIFS(销售明细!$K$2:$K$121,销售明细!$E$2:$E$121,$A31) | D31: =IF(B31=0,0,C31/B31) | E31: =IF($B$33=0,0,B31/$B$33)
A32: 办公耗材 | B32: =SUMIFS(销售明细!$J$2:$J$121,销售明细!$E$2:$E$121,$A32) | C32: =SUMIFS(销售明细!$K$2:$K$121,销售明细!$E$2:$E$121,$A32) | D32: =IF(B32=0,0,C32/B32) | E32: =IF($B$33=0,0,B32/$B$33)
A33: 合计 | B33: =SUM(B28:B32) | C33: =SUM(C28:C32) | D33: =IF(B33=0,0,C33/B33) | E33: =SUM(E28:E32)
A35: 销售员业绩
A36: 销售员 | B36: 所属区域 | C36: 销售额 | D36: 毛利 | E36: 毛利率
A37: 张伟 | B37: 华东 | C37: =SUMIFS(销售明细!$J$2:$J$121,销售明细!$D$2:$D$121,$A37) | D37: =SUMIFS(销售明细!$K$2:$K$121,销售明细!$D$2:$D$121,$A37) | E37: =IF(C37=0,0,D37/C37)
A38: 李娜 | B38: 华东 | C38: =SUMIFS(销售明细!$J$2:$J$121,销售明细!$D$2:$D$121,$A38) | D38: =SUMIFS(销售明细!$K$2:$K$121,销售明细!$D$2:$D$121,$A38) | E38: =IF(C38=0,0,D38/C38)
A39: 王强 | B39: 华南 | C39: =SUMIFS(销售明细!$J$2:$J$121,销售明细!$D$2:$D$121,$A39) | D39: =SUMIFS(销售明细!$K$2:$K$121,销售明细!$D$2:$D$121,$A39) | E39: =IF(C39=0,0,D39/C39)
A40: 刘洋 | B40: 华南 | C40: =SUMIFS(销售明细!$J$2:$J$121,销售明细!$D$2:$D$121,$A40) | D40: =SUMIFS(销售明细!$K$2:$K$121,销售明细!$D$2:$D$121,$A40) | E40: =IF(C40=0,0,D40/C40)
A41: 陈静 | B41: 华北 | C41: =SUMIFS(销售明细!$J$2:$J$121,销售明细!$D$2:$D$121,$A41) | D41: =SUMIFS(销售明细!$K$2:$K$121,销售明细!$D$2:$D$121,$A41) | E41: =IF(C41=0,0,D41/C41)
A42: 周敏 | B42: 华北 | C42: =SUMIFS(销售明细!$J$2:$J$121,销售明细!$D$2:$D$121,$A42) | D42: =SUMIFS(销售明细!$K$2:$K$121,销售明细!$D$2:$D$121,$A42) | E42: =IF(C42=0,0,D42/C42)
A43: 赵磊 | B43: 西南 | C43: =SUMIFS(销售明细!$J$2:$J$121,销售明细!$D$2:$D$121,$A43) | D43: =SUMIFS(销售明细!$K$2:$K$121,销售明细!$D$2:$D$121,$A43) | E43: =IF(C43=0,0,D43/C43)
A44: 孙悦 | B44: 华中 | C44: =SUMIFS(销售明细!$J$2:$J$121,销售明细!$D$2:$D$121,$A44) | D44: =SUMIFS(销售明细!$K$2:$K$121,销售明细!$D$2:$D$121,$A44) | E44: =IF(C44=0,0,D44/C44)
A45: 合计 | C45: =SUM(C37:C44) | D45: =SUM(D37:D44) | E45: =IF(C45=0,0,D45/C45)

Sheet 销售明细
A1: 日期 | B1: 订单编号 | C1: 区域 | D1: 销售员 | E1: 产品类别 | F1: 产品名称 | G1: 数量 | H1: 单价 | I1: 单位成本 | J1: 销售额 | K1: 毛利 | L1: 毛利率 | M1: 月份
A2: 46023 | B2: SO20260068 | C2: 华东 | D2: 李娜 | E2: 办公耗材 | F2: A4 复印纸 (箱) | G2: 7 | H2: 128 | I2: 88 | J2: =G2*H2 | K2: =J2-G2*I2 | L2: =IF(J2=0,0,K2/J2) | M2: =MONTH(A2)
A3: 46025 | B3: SO20260114 | C3: 华北 | D3: 陈静 | E3: 存储设备 | F3: 移动固态硬盘 1TB | G3: 6 | H3: 699 | I3: 512 | J3: =G3*H3 | K3: =J3-G3*I3 | L3: =IF(J3=0,0,K3/J3) | M3: =MONTH(A3)
A4: 46026 | B4: SO20260071 | C4: 华南 | D4: 王强 | E4: 显示器 | F4: 27吋 2K 显示器 | G4: 1 | H4: 1299 | I4: 968 | J4: =G4*H4 | K4: =J4-G4*I4 | L4: =IF(J4=0,0,K4/J4) | M4: =MONTH(A4)
A5: 46026 | B5: SO20260092 | C5: 华东 | D5: 张伟 | E5: 键鼠外设 | F5: 无线鼠标 M5 | G5: 4 | H5: 149 | I5: 92 | J5: =G5*H5 | K5: =J5-G5*I5 | L5: =IF(J5=0,0,K5/J5) | M5: =MONTH(A5)
A6: 46031 | B6: SO20260002 | C6: 西南 | D6: 赵磊 | E6: 办公耗材 | F6: 激光硒鼓 | G6: 17 | H6: 259 | I6: 178 | J6: =G6*H6 | K6: =J6-G6*I6 | L6: =IF(J6=0,0,K6/J6) | M6: =MONTH(A6)
A7: 46031 | B7: SO20260094 | C7: 华北 | D7: 周敏 | E7: 办公耗材 | F7: A4 复印纸 (箱) | G7: 10 | H7: 128 | I7: 88 | J7: =G7*H7 | K7: =J7-G7*I7 | L7: =IF(J7=0,0,K7/J7) | M7: =MONTH(A7)
A8: 46031 | B8: SO20260106 | C8: 华南 | D8: 刘洋 | E8: 显示器 | F8: 27吋 2K 显示器 | G8: 1 | H8: 1299 | I8: 968 | J8: =G8*H8 | K8: =J8-G8*I8 | L8: =IF(J8=0,0,K8/J8) | M8: =MONTH(A8)
A9: 46032 | B9: SO20260037 | C9: 华东 | D9: 张伟 | E9: 笔记本电脑 | F9: 星辰 14 Pro 笔记本 | G9: 3 | H9: 5299 | I9: 4180 | J9: =G9*H9 | K9: =J9-G9*I9 | L9: =IF(J9=0,0,K9/J9) | M9: =MONTH(A9)
A10: 46033 | B10: SO20260017 | C10: 华南 | D10: 王强 | E10: 存储设备 | F10: 移动固态硬盘 1TB | G10: 5 | H10: 699 | I10: 512 | J10: =G10*H10 | K10: =J10-G10*I10 | L10: =IF(J10=0,0,K10/J10) | M10: =MONTH(A10)
A11: 46034 | B11: SO20260005 | C11: 华南 | D11: 刘洋 | E11: 办公耗材 | F11: 激光硒鼓 | G11: 7 | H11: 259 | I11: 178 | J11: =G11*H11 | K11: =J11-G11*I11 | L11: =IF(J11=0,0,K11/J11) | M11: =MONTH(A11)
A12: 46035 | B12: SO20260063 | C12: 华北 | D12: 周敏 | E12: 显示器 | F12: 27吋 2K 显示器 | G12: 1 | H12: 1299 | I12: 968 | J12: =G12*H12 | K12: =J12-G12*I12 | L12: =IF(J12=0,0,K12/J12) | M12: =MONTH(A12)
A13: 46037 | B13: SO20260120 | C13: 西南 | D13: 赵磊 | E13: 显示器 | F13: 32吋 4K 显示器 | G13: 4 | H13: 2499 | I13: 1890 | J13: =G13*H13 | K13: =J13-G13*I13 | L13: =IF(J13=0,0,K13/J13) | M13: =MONTH(A13)
... A121: 46201 | B121: SO20260119 | C121: 华南 | D121: 王强 | E121: 键鼠外设 | F121: 无线鼠标 M5 | G121: 3 | H121: 149 | I121: 92 | J121: =G121*H121 | K121: =J121-G121*I121 | L121: =IF(J121=0,0,K121/J121) | M121: =MONTH(A121)

Sheet 参数设置
A1: 参数与目标设置
A2: 蓝色字体为可调整参数，修改后“看板”自动刷新
A4: 区域 | B4: 半年目标(元)
A5: 华东 | B5: 140000
A6: 华南 | B6: 130000
A7: 华北 | B7: 140000
A8: 西南 | B8: 90000
A9: 华中 | B9: 90000
A10: 合计 | B10: =SUM(B5:B9)

Sheet 说明
A1: 使用说明与数据口径
A3: 【数据范围】2026-01-01 至 2026-06-30，共 120 笔订单，覆盖 5 个区域、8 名销售员、5 个产品类别。
A4: 【数据来源】本表为模板演示用的模拟数据。把“销售明细”中的内容替换为真实流水，看板即自动重算。
A5: 【计算口径】销售额 = 数量 × 单价；毛利 = 销售额 − 数量 × 单位成本；毛利率 = 毛利 ÷ 销售额；占比 = 明细项 ÷ 合计。
A6: 【颜色约定】蓝色字体 = 需人工填写、可随时调整的参数；黑色字体 = 公式自动计算；绿色字体 = 引用其他工作表的数据。
A7: 【更新方式】在“销售明细”追加数据行后，请同步把看板中 SUMIFS/COUNTIF 的区间从第 121 行扩展到新的末行。
A8: 【目标维护】在“参数设置”表调整各区域半年目标，看板的“达成率”与数据条会自动刷新。
A9: 【制作说明】看板未使用 Excel 图表对象，改用单元格内数据条（条件格式），因此在任何 Excel / WPS 版本中都能原样显示。
